{"data":{"markers":{"edges":[{"node":{"id":"0e3f7c4d-0005-5f41-9946-c60d13f1c389","color":"#910b2f","latlng":{"lat":22.6203348,"lng":120.3120375},"events":[{"id":"236925aa-e54e-5bfe-b5a9-6e8cb9b07c59","name":"高雄敏捷之旅2018 (Agile Tour Kaohsiung 2018) ~ 南台灣最大敏捷盛會","location":"DAKUO | 高雄市數位內容創意中心 / 80341高雄市鹽埕區七賢三路123號3樓","dateTime":"2 天內"},{"id":"fc1403cd-c43f-570f-8187-df67c6f191ef","name":"HP4KH - 聖誕節讀書會","location":"DAKUO | 高雄市數位內容創意中心 / 高雄市鹽埕區七賢三路123號3樓","dateTime":"11 天內"},{"id":"e8f08fa1-d878-52bb-9fb9-4ba836471572","name":"KaLUG 1812聚會: Alberich - Coq / Louis - GIS 系统","location":"【高雄】Tady Coffe / 高雄市三民區旅順街8號","dateTime":"17 天內"}]}},{"node":{"id":"10f484cc-a80b-5d6e-acad-fca06a9c6a11","color":"#069e5c","latlng":{"lat":25.0375198,"lng":121.5636796},"events":[{"id":"5497eca5-b7c3-54b2-9992-31a42d83ec4e","name":"台灣駭客年會 HITCON Pacific 2018","location":"台北文創 / 臺北市信義區菸廠路 88 號 6 樓","dateTime":"9 小時內"},{"id":"10b5a4a8-479b-5427-8781-2624242152ca","name":"TWJUG 2018 十二月份聚會 - gRPC","location":"cacaFly 國際交誼廳  / 106台北市大安區敦化南路二段2號 16樓","dateTime":"2 天內"},{"id":"dad73794-5938-5767-bebb-4cb9e6d67615","name":"DevOps Taiwan Meetup #19 - 那些年我們踩的 CI 坑 ","location":"天瓏資訊圖書 CodingSpace (台北市重慶南路一段105號2樓)  / 台北市重慶南路一段105號2樓","dateTime":"2 天內"},{"id":"ed85f01e-dfc4-5fdd-8593-c263fd23bbec","name":"TWJUG 2018 十二月份聚會 - Serverless Java","location":"cacaFly 國際交誼廳  / 106台北市大安區敦化南路二段2號 16樓","dateTime":"5 天內"},{"id":"f132c3c8-421b-5a5a-9f4d-fdc1d15d46f6","name":"Agile Tour Taichung 2018-12 台中敏捷之旅 ","location":"台中市逢甲大學資訊電機館 / 台中市西屯區文華路100號","dateTime":"10 天內"},{"id":"4feacdaa-0e04-5581-bbb2-376b9ffbd7dd","name":"SITCON 2019 個人小額贊助方案","location":"中央研究院人文社會科學館 國際會議廳  / 台北市南港區研究院路二段128號","dateTime":"3 個月內"},{"id":"22931013-fb36-5ad7-ab7e-bf90757b3698","name":"SITCON 2019 個人小額贊助方案-純粹贊助","location":"中央研究院人文社會科學館 國際會議廳  / 台北市南港區研究院路二段128號","dateTime":"3 個月內"}]}},{"node":{"id":"05012ad1-fe55-5fb5-ad63-5a16f5ece765","color":"#03721d","latlng":{"lat":24.819185256958008,"lng":121.02629852294922},"events":[{"id":"2b96cb43-cdd9-54c0-a5ef-1a81e85d0a08","name":"SyntaxError","location":"Micro Beer 麥烤杯","dateTime":"5 小時前"},{"id":"70378020-2355-57a0-acbc-dd419bff2149","name":"從零開始理解原始碼 - 以 ethereum 為例","location":"Micro Beer 麥烤杯","dateTime":"7 天內"},{"id":"6af29e4d-ee5d-53c7-abcf-d4c01aaaecf1","name":"SyntaxError","location":"Micro Beer 麥烤杯","dateTime":"14 天內"}]}},{"node":{"id":"5ab9a921-17c2-585f-ad2c-ce14953fb1f7","color":"#061282","latlng":{"lat":25.04805564880371,"lng":121.55213165283203},"events":[{"id":"ddc1b70e-c8f2-55b4-b7b4-124bfdef2834","name":"[Visualization Series] 公投資料視覺化與選舉分析","location":"urAD優愛德","dateTime":"12 天內"}]}},{"node":{"id":"e841f239-4623-5f68-9a59-761f940f4f38","color":"#099e8f","latlng":{"lat":25.081464767456055,"lng":121.56625366210938},"events":[{"id":"89b18f0f-726a-5977-81b6-d4acb50e30d4","name":"HyperLedger 實作小聚","location":"管地有限公司 Gandi Asia Co. Ltd","dateTime":"8 天內"}]}},{"node":{"id":"2a4725b1-4f07-54d1-b058-f712d70cbb24","color":"#c9b90e","latlng":{"lat":25.038726806640625,"lng":121.5414047241211},"events":[{"id":"bf328368-d92a-5164-a576-741e86cff952","name":"MLDM Monday x Julia | Julia Tutorial III","location":"社會創新實驗中心 (2樓A-5教室)","dateTime":"2 天前"},{"id":"4467e46a-8139-5843-a1d0-a7b4fbdfa3fd","name":"MLDM Monday｜相親配對與大數據 Marriage Matchmaking and Big Data: Economists vs Machines","location":"社會創新實驗中心 (2樓A-5教室)","dateTime":"5 天內"},{"id":"005fd4d0-cf88-5510-9ff1-af4403dd2d09","name":"MLDM Monday｜自駕車學走路 - 從 Donkey Car 蹣跚學步談起 [Part 2]","location":"社會創新實驗中心 (2樓A-5教室)","dateTime":"1 個月內"},{"id":"27ab78a8-432d-5986-bf45-69f19ccebcf4","name":"MLDM Monday x Julia | Julia Tutorial IV","location":"社會創新實驗中心 (2樓A-5教室)","dateTime":"1 個月內"}]}},{"node":{"id":"278a0beb-560f-5f00-a71c-0e0605e1cf4c","color":"#1a067c","latlng":{"lat":25.040504455566406,"lng":121.56689453125},"events":[{"id":"fc125783-cc4a-540a-8698-56b4212fc094","name":"Global AI Bootcamp - Taipei","location":"台灣微軟(新址）","dateTime":"2 天內"}]}},{"node":{"id":"e3f91859-5a7d-5e85-ba25-ff8c924548ee","color":"#bc1c10","latlng":{"lat":25.04241943359375,"lng":121.51386260986328},"events":[{"id":"1e3cd309-2b6e-56d9-8d57-ab43bed3ff19","name":"Elixir台灣 台北 Meetup #","location":"五倍紅寶石","dateTime":"1 個月內"}]}},{"node":{"id":"094ec90b-cec3-57d7-a69e-c9765010881e","color":"#0f9635","latlng":{"lat":25.039670944213867,"lng":121.53105163574219},"events":[{"id":"9832bf48-ffa2-5722-befc-3ee29bf42271","name":"HackingThursday 固定聚會","location":"田中園 光華店","dateTime":"20 小時內"},{"id":"df14d59e-d7f7-5c6f-8071-08744334b465","name":"HackingThursday 固定聚會","location":"田中園 光華店","dateTime":"8 天內"},{"id":"d9950b1e-82e4-5d7f-9589-9442c7faeecd","name":"HackingThursday 固定聚會","location":"田中園 光華店","dateTime":"15 天內"}]}},{"node":{"id":"77708c7c-9943-5a86-87d6-15ce63bb63ed","color":"#991c06","latlng":{"lat":24.8066333,"lng":120.9686833},"events":[{"id":"ea417e9d-c522-50cb-885b-c64174ccc9f2","name":"12/13 Raymond Lai 分享 ”矽谷科技新創剖析“","location":"TAB-Tea and Beverages / 新竹市大學路 78 號","dateTime":"20 小時內"}]}}]}},"pageContext":{}}