{"data":{"event":{"id":"5497eca5-b7c3-54b2-9992-31a42d83ec4e","name":"台灣駭客年會 HITCON Pacific 2018","link":"https://hitcon.kktix.cc/events/hitcon-pacific-2018","color":"#211e1e","local_city":"Taipei","location":"台北文創 / 臺北市信義區菸廠路 88 號 6 樓","geocode":{"lat":25.0375198,"lng":121.5636796},"geocodeFromGroup":"false","dateTime":"01:00 12/13/2018 (星期四)","group":{"id":"e8eb5d3e-28ce-5119-b342-0fc03725a3f2","title":"Hacks In Taiwan Conference","logo_url":"https://t.kfs.io/upload_images/34020/hitcon2012-social-logo_512x512_promote.png","city":"Taipei","registration":{"type":"kktix","url":"https://hitcon.kktix.cc/"},"category":{"name":"conference"}},"marker":{"id":"10f484cc-a80b-5d6e-acad-fca06a9c6a11","color":"#069e5c","latlng":{"lat":25.0375198,"lng":121.5636796}}}},"pageContext":{"eventId":"5497eca5-b7c3-54b2-9992-31a42d83ec4e"}}