{"data":{"event":{"id":"93586fc5-31e4-53b8-b89b-b1134043e31a","name":"Hacktoberfest in DigitalOcean Hsinchu - A Celebration of Open Source!","link":"https://www.meetup.com/DigitalOceanHsinchu/events/254838164/","color":"#0080FF","local_city":"Hsinchu","location":"TAB-Tea and Beverages","geocode":{"lat":24.78961944580078,"lng":121.00019836425781},"geocodeFromGroup":"false","dateTime":"05:00 10/06/2018 (星期六)","group":{"id":"1599250c-d723-5666-a291-3e8e8c334637","title":"DigitalOcean Hsinchu","logoURL":"https://www.digitalocean.com/apple-touch-icon.png","city":"Hsinchu","registration":{"type":"meetup","url":"https://www.meetup.com/DigitalOceanHsinchu/"},"category":{"name":"community"}},"marker":{"id":"f49f5d0d-bb4e-558f-a6d3-bed6e8598893","color":"#ce0cc8","latlng":{"lat":24.78961944580078,"lng":121.00019836425781}}}},"pageContext":{"eventId":"93586fc5-31e4-53b8-b89b-b1134043e31a"}}